[
	{"p1":"奔腾电动剃须刀Povos/奔腾 PS5200","picurl_0":"a_01.jpg","p_01":"RNB:96.00","p2":"可用商城积分：0.00","p_011":"96.00"},
	{"p1":"奔腾电动剃须刀Povos/奔腾 PS5200","picurl_0":"a_02.jpg","p_01":"RNB:79.00","p2":"可用商城积分：0.00","p_011":"96.00"},
	{"p1":"奔腾电动剃须刀Povos/奔腾 PS5200","picurl_0":"a_03.jpg","p_01":"RNB:79.00","p2":"可用商城积分：0.00","p_011":"96.00"},
	{"p1":"奔腾电动剃须刀Povos/奔腾 PS5200","picurl_0":"a_04.jpg","p_01":"RNB:95.00","p2":"可用商城积分：0.00","p_011":"96.00"},
	{"p1":"奔腾电动剃须刀Povos/奔腾 PS5200","picurl_0":"a_05.jpg","p_01":"RNB:95.00","p2":"可用商城积分：0.00","p_011":"96.00"},
	{"p1":"奔腾电动剃须刀Povos/奔腾 PS5200","picurl_0":"a_06.jpg","p_01":"RNB:110.00","p2":"可用商城积分：0.00","p_011":"96.00"},
	{"p1":"奔腾电动剃须刀Povos/奔腾 PS5200","picurl_0":"a_07.jpg","p_01":"RNB:119.00","p2":"可用商城积分：0.00","p_011":"96.00"},
	{"p1":"奔腾电动剃须刀Povos/奔腾 PS5200","picurl_0":"a_08.jpg","p_01":"RNB:129.00","p2":"可用商城积分：0.00","p_011":"96.00"},
	{"p1":"奔腾电动剃须刀Povos/奔腾 PS5200","picurl_0":"a_09.jpg","p_01":"RNB:129.00","p2":"可用商城积分：0.00","p_011":"96.00"},
	{"p1":"奔腾电动剃须刀Povos/奔腾 PS5200","picurl_0":"a_10.jpg","p_01":"RNB:145.00","p2":"可用商城积分：0.00","p_011":"96.00"},
	{"p1":"奔腾电动剃须刀Povos/奔腾 PS5200","picurl_0":"a_11.jpg","p_01":"RNB:149.00","p2":"可用商城积分：0.00","p_011":"96.00"},
	{"p1":"奔腾电动剃须刀Povos/奔腾 PS5200","picurl_0":"a_12.jpg","p_01":"RNB:178.00","p2":"可用商城积分：0.00","p_011":"96.00"},
	{"p1":"奔腾电动剃须刀Povos/奔腾 PS5200","picurl_0":"a_13.jpg","p_01":"RNB:179.00","p2":"可用商城积分：0.00","p_011":"96.00"},
	{"p1":"奔腾电动剃须刀Povos/奔腾 PS5200","picurl_0":"a_14.jpg","p_01":"RNB:199.00","p2":"可用商城积分：0.00","p_011":"96.00"},
	{"p1":"奔腾电动剃须刀Povos/奔腾 PS5200","picurl_0":"a_15.jpg","p_01":"RNB:199.00","p2":"可用商城积分：0.00","p_011":"96.00"},
	{"p1":"奔腾电动剃须刀Povos/奔腾 PS5200","picurl_0":"a_16.jpg","p_01":"RNB:219.00","p2":"可用商城积分：0.00","p_011":"96.00"},
	{"p1":"奔腾电动剃须刀Povos/奔腾 PS5200","picurl_0":"a_17.jpg","p_01":"RNB:210.00","p2":"可用商城积分：0.00","p_011":"96.00"},
	{"p1":"奔腾电动剃须刀Povos/奔腾 PS5200","picurl_0":"a_18.jpg","p_01":"RNB:220.00","p2":"可用商城积分：0.00","p_011":"96.00"},
	{"p1":"奔腾电动剃须刀Povos/奔腾 PS5200","picurl_0":"a_19.jpg","p_01":"RNB:221.00","p2":"可用商城积分：0.00","p_011":"96.00"},
	{"p1":"奔腾电动剃须刀Povos/奔腾 PS5200","picurl_0":"a_20.jpg","p_01":"RNB:246.00","p2":"可用商城积分：0.00","p_011":"96.00"},
	{"p1":"奔腾电动剃须刀Povos/奔腾 PS5200","picurl_0":"a_01.jpg","p_01":"RNB:96.00","p2":"可用商城积分：0.00","p_011":"96.00"},
	{"p1":"奔腾电动剃须刀Povos/奔腾 PS5200","picurl_0":"a_02.jpg","p_01":"RNB:79.00","p2":"可用商城积分：0.00","p_011":"96.00"},
	{"p1":"奔腾电动剃须刀Povos/奔腾 PS5200","picurl_0":"a_03.jpg","p_01":"RNB:79.00","p2":"可用商城积分：0.00","p_011":"96.00"},
	{"p1":"奔腾电动剃须刀Povos/奔腾 PS5200","picurl_0":"a_04.jpg","p_01":"RNB:95.00","p2":"可用商城积分：0.00","p_011":"96.00"},
	{"p1":"奔腾电动剃须刀Povos/奔腾 PS5200","picurl_0":"a_05.jpg","p_01":"RNB:95.00","p2":"可用商城积分：0.00","p_011":"96.00"},
	{"p1":"奔腾电动剃须刀Povos/奔腾 PS5200","picurl_0":"a_06.jpg","p_01":"RNB:110.00","p2":"可用商城积分：0.00","p_011":"96.00"},
	{"p1":"奔腾电动剃须刀Povos/奔腾 PS5200","picurl_0":"a_07.jpg","p_01":"RNB:119.00","p2":"可用商城积分：0.00","p_011":"96.00"},
	{"p1":"奔腾电动剃须刀Povos/奔腾 PS5200","picurl_0":"a_08.jpg","p_01":"RNB:129.00","p2":"可用商城积分：0.00","p_011":"96.00"},
	{"p1":"奔腾电动剃须刀Povos/奔腾 PS5200","picurl_0":"a_09.jpg","p_01":"RNB:129.00","p2":"可用商城积分：0.00","p_011":"96.00"},
	{"p1":"奔腾电动剃须刀Povos/奔腾 PS5200","picurl_0":"a_10.jpg","p_01":"RNB:145.00","p2":"可用商城积分：0.00","p_011":"96.00"},
	{"p1":"奔腾电动剃须刀Povos/奔腾 PS5200","picurl_0":"a_11.jpg","p_01":"RNB:149.00","p2":"可用商城积分：0.00","p_011":"96.00"},
	{"p1":"奔腾电动剃须刀Povos/奔腾 PS5200","picurl_0":"a_12.jpg","p_01":"RNB:178.00","p2":"可用商城积分：0.00","p_011":"96.00"},
	{"p1":"奔腾电动剃须刀Povos/奔腾 PS5200","picurl_0":"a_13.jpg","p_01":"RNB:179.00","p2":"可用商城积分：0.00","p_011":"96.00"},
	{"p1":"奔腾电动剃须刀Povos/奔腾 PS5200","picurl_0":"a_14.jpg","p_01":"RNB:199.00","p2":"可用商城积分：0.00","p_011":"96.00"},
	{"p1":"奔腾电动剃须刀Povos/奔腾 PS5200","picurl_0":"a_15.jpg","p_01":"RNB:199.00","p2":"可用商城积分：0.00","p_011":"96.00"},
	{"p1":"奔腾电动剃须刀Povos/奔腾 PS5200","picurl_0":"a_16.jpg","p_01":"RNB:219.00","p2":"可用商城积分：0.00","p_011":"96.00"},
	{"p1":"奔腾电动剃须刀Povos/奔腾 PS5200","picurl_0":"a_17.jpg","p_01":"RNB:210.00","p2":"可用商城积分：0.00","p_011":"96.00"},
	{"p1":"奔腾电动剃须刀Povos/奔腾 PS5200","picurl_0":"a_18.jpg","p_01":"RNB:220.00","p2":"可用商城积分：0.00","p_011":"96.00"},
	{"p1":"奔腾电动剃须刀Povos/奔腾 PS5200","picurl_0":"a_19.jpg","p_01":"RNB:221.00","p2":"可用商城积分：0.00","p_011":"96.00"},
	{"p1":"奔腾电动剃须刀Povos/奔腾 PS5200","picurl_0":"a_20.jpg","p_01":"RNB:246.00","p2":"可用商城积分：0.00","p_011":"96.00"},
	{"p1":"奔腾电动剃须刀Povos/奔腾 PS5200","picurl_0":"a_01.jpg","p_01":"RNB:96.00","p2":"可用商城积分：0.00","p_011":"96.00"},
	{"p1":"奔腾电动剃须刀Povos/奔腾 PS5200","picurl_0":"a_02.jpg","p_01":"RNB:79.00","p2":"可用商城积分：0.00","p_011":"96.00"},
	{"p1":"奔腾电动剃须刀Povos/奔腾 PS5200","picurl_0":"a_03.jpg","p_01":"RNB:79.00","p2":"可用商城积分：0.00","p_011":"96.00"},
	{"p1":"奔腾电动剃须刀Povos/奔腾 PS5200","picurl_0":"a_04.jpg","p_01":"RNB:95.00","p2":"可用商城积分：0.00","p_011":"96.00"},
	{"p1":"奔腾电动剃须刀Povos/奔腾 PS5200","picurl_0":"a_05.jpg","p_01":"RNB:95.00","p2":"可用商城积分：0.00","p_011":"96.00"},
	{"p1":"奔腾电动剃须刀Povos/奔腾 PS5200","picurl_0":"a_06.jpg","p_01":"RNB:110.00","p2":"可用商城积分：0.00","p_011":"96.00"},
	{"p1":"奔腾电动剃须刀Povos/奔腾 PS5200","picurl_0":"a_07.jpg","p_01":"RNB:119.00","p2":"可用商城积分：0.00","p_011":"96.00"},
	{"p1":"奔腾电动剃须刀Povos/奔腾 PS5200","picurl_0":"a_08.jpg","p_01":"RNB:129.00","p2":"可用商城积分：0.00","p_011":"96.00"},
	{"p1":"奔腾电动剃须刀Povos/奔腾 PS5200","picurl_0":"a_09.jpg","p_01":"RNB:129.00","p2":"可用商城积分：0.00","p_011":"96.00"},
	{"p1":"奔腾电动剃须刀Povos/奔腾 PS5200","picurl_0":"a_10.jpg","p_01":"RNB:145.00","p2":"可用商城积分：0.00","p_011":"96.00"},
	{"p1":"奔腾电动剃须刀Povos/奔腾 PS5200","picurl_0":"a_11.jpg","p_01":"RNB:149.00","p2":"可用商城积分：0.00","p_011":"96.00"},
	{"p1":"奔腾电动剃须刀Povos/奔腾 PS5200","picurl_0":"a_12.jpg","p_01":"RNB:178.00","p2":"可用商城积分：0.00","p_011":"96.00"},
	{"p1":"奔腾电动剃须刀Povos/奔腾 PS5200","picurl_0":"a_13.jpg","p_01":"RNB:179.00","p2":"可用商城积分：0.00","p_011":"96.00"},
	{"p1":"奔腾电动剃须刀Povos/奔腾 PS5200","picurl_0":"a_14.jpg","p_01":"RNB:199.00","p2":"可用商城积分：0.00","p_011":"96.00"},
	{"p1":"奔腾电动剃须刀Povos/奔腾 PS5200","picurl_0":"a_15.jpg","p_01":"RNB:199.00","p2":"可用商城积分：0.00","p_011":"96.00"},
	{"p1":"奔腾电动剃须刀Povos/奔腾 PS5200","picurl_0":"a_16.jpg","p_01":"RNB:219.00","p2":"可用商城积分：0.00","p_011":"96.00"},
	{"p1":"奔腾电动剃须刀Povos/奔腾 PS5200","picurl_0":"a_17.jpg","p_01":"RNB:210.00","p2":"可用商城积分：0.00","p_011":"96.00"},
	{"p1":"奔腾电动剃须刀Povos/奔腾 PS5200","picurl_0":"a_18.jpg","p_01":"RNB:220.00","p2":"可用商城积分：0.00","p_011":"96.00"},
	{"p1":"奔腾电动剃须刀Povos/奔腾 PS5200","picurl_0":"a_19.jpg","p_01":"RNB:221.00","p2":"可用商城积分：0.00","p_011":"96.00"},
	{"p1":"奔腾电动剃须刀Povos/奔腾 PS5200","picurl_0":"a_20.jpg","p_01":"RNB:246.00","p2":"可用商城积分：0.00","p_011":"96.00"}
]
